gso/__init__.py
gso/action.py
gso/globalstate.py
gso/observable.py
gso/observer.py
gso-2.0.1.dist-info/LICENSE
gso-2.0.1.dist-info/METADATA
gso-2.0.1.dist-info/WHEEL
gso-2.0.1.dist-info/top_level.txt
gso-2.0.1.dist-info/RECORD
