Metadata-Version: 2.1
Name: gso
Version: 2.0.1
Summary: An open-source Python library for managing application state.
Home-page: https://github.com/youssef-attai/gso
Author: Youssef Atta'i
Author-email: youssefgalalnazem@gmail.com
Project-URL: Bug Tracker, https://github.com/youssef-attai/gso/issues
Classifier: Programming Language :: Python :: 3
Classifier: License :: OSI Approved :: MIT License
Classifier: Operating System :: OS Independent
Requires-Python: >=3.10
License-File: LICENSE
